awslabs/__init__.py
awslabs/aws_documentation_mcp_server/__init__.py
awslabs/aws_documentation_mcp_server/models.py
awslabs/aws_documentation_mcp_server/server.py
awslabs/aws_documentation_mcp_server/server_aws.py
awslabs/aws_documentation_mcp_server/server_aws_cn.py
awslabs/aws_documentation_mcp_server/server_utils.py
awslabs/aws_documentation_mcp_server/util.py
iflow_mcp_awslabs_aws_documentation_mcp_server-1.1.14.dist-info/METADATA
iflow_mcp_awslabs_aws_documentation_mcp_server-1.1.14.dist-info/WHEEL
iflow_mcp_awslabs_aws_documentation_mcp_server-1.1.14.dist-info/entry_points.txt
iflow_mcp_awslabs_aws_documentation_mcp_server-1.1.14.dist-info/licenses/LICENSE
iflow_mcp_awslabs_aws_documentation_mcp_server-1.1.14.dist-info/licenses/NOTICE
iflow_mcp_awslabs_aws_documentation_mcp_server-1.1.14.dist-info/RECORD
